wind2json/__init__.py
wind2json-1.0.4.dist-info/LICENSE
wind2json-1.0.4.dist-info/METADATA
wind2json-1.0.4.dist-info/WHEEL
wind2json-1.0.4.dist-info/top_level.txt
wind2json-1.0.4.dist-info/RECORD
