Metadata-Version: 2.1
Name: wind2json
Version: 1.0.4
Summary: decode CMA grid-wind product
Author: pysoer
Author-email: 413188893@qq.com
License: GPL Licence
Platform: Windows
Requires-Python: >=3.5
License-File: LICENSE
Requires-Dist: meteva
